GlobalEmail
GlobalFiles
GlobalTables
GlobalUi
