Metadata-Version: 2.1
Name: GlobalRPA_Lib
Version: 1.4.0
Summary: Library RPA Python
Author: Mateus Orlandin Dias
Author-email: mateus.orlandin@gmail.com
License: MIT License
Keywords: RPA activities
License-File: LICENCE
Requires-Dist: secure-smtplib
Requires-Dist: selenium
